fASP/__init__.py
fASP/bnet.py
fASP/fASP.py
fASP/naive.py
fasp-0.3.0.dist-info/METADATA
fasp-0.3.0.dist-info/WHEEL
fasp-0.3.0.dist-info/entry_points.txt
fasp-0.3.0.dist-info/licenses/LICENSE
fasp-0.3.0.dist-info/RECORD
